robust_email_validator/__init__.py
robust_email_validator/config.py
robust_email_validator/schemas/email.py
robust_email_validator/services/__init__.py
robust_email_validator/services/email_validator.py
robust_email_validator/utils/__init__.py
robust_email_validator/utils/disposable_checker.py
robust_email_validator/utils/dns_checker.py
robust_email_validator-0.1.0.dist-info/LICENSE
robust_email_validator-0.1.0.dist-info/METADATA
robust_email_validator-0.1.0.dist-info/WHEEL
robust_email_validator-0.1.0.dist-info/top_level.txt
robust_email_validator-0.1.0.dist-info/RECORD
