Metadata-Version: 2.1
Name: robust_email_validator
Version: 0.1.0
Summary: Validate Your Email
Requires-Python: >=3.10
License-File: LICENSE
Requires-Dist: dnspython >=2.7.0
Requires-Dist: pydantic >=2.9.2
Requires-Dist: requests >=2.32.3
